{
  "TRANSLATION_UNIT:'/pcl/tools/oni2pcd.cpp'": {
    "children": [
      {
        "FUNCTION_DECL:'cloud_cb'": {
          "children": [
            {
              "COMPOUND_STMT:''": {
                "children": [
                  {
                    "DECL_STMT:''": {
                      "children": [
                        "VAR_DECL:'w'"
                      ]
                    }
                  },
                  {
                    "UNARY_OPERATOR:''": {
                      "children": [
                        "DECL_REF_EXPR:'i'"
                      ]
                    }
                  }
                ]
              }
            },
            "PARM_DECL:'cloud'"
          ]
        }
      },
      {
        "FUNCTION_DECL:'main'": {
          "children": [
            {
              "COMPOUND_STMT:''": {
                "children": [
                  {
                    "DECL_STMT:''": {
                      "children": [
                        "VAR_DECL:'grabber'"
                      ]
                    }
                  },
                  {
                    "DECL_STMT:''": {
                      "children": [
                        "VAR_DECL:'c'"
                      ]
                    }
                  },
                  {
                    "IF_STMT:''": {
                      "children": [
                        {
                          "BINARY_OPERATOR:''": {
                            "children": [
                              "INTEGER_LITERAL:''",
                              {
                                "UNEXPOSED_EXPR:'argc'": {
                                  "children": [
                                    "DECL_REF_EXPR:'argc'"
                                  ]
                                }
                              }
                            ]
                          }
                        },
                        {
                          "COMPOUND_STMT:''": {
                            "children": [
                              {
                                "CALL_EXPR:'printHelp'": {
                                  "children": [
                                    {
                                      "UNEXPOSED_EXPR:'argc'": {
                                        "children": [
                                          "DECL_REF_EXPR:'argc'"
                                        ]
                                      }
                                    },
                                    {
                                      "UNEXPOSED_EXPR:'argv'": {
                                        "children": [
                                          "DECL_REF_EXPR:'argv'"
                                        ]
                                      }
                                    },
                                    {
                                      "UNEXPOSED_EXPR:'printHelp'": {
                                        "children": [
                                          "DECL_REF_EXPR:'printHelp'"
                                        ]
                                      }
                                    }
                                  ]
                                }
                              },
                              {
                                "RETURN_STMT:''": {
                                  "children": [
                                    {
                                      "PAREN_EXPR:''": {
                                        "children": [
                                          {
                                            "UNARY_OPERATOR:''": {
                                              "children": [
                                                "INTEGER_LITERAL:''"
                                              ]
                                            }
                                          }
                                        ]
                                      }
                                    }
                                  ]
                                }
                              }
                            ]
                          }
                        }
                      ]
                    }
                  },
                  {
                    "RETURN_STMT:''": {
                      "children": [
                        {
                          "PAREN_EXPR:''": {
                            "children": [
                              "INTEGER_LITERAL:''"
                            ]
                          }
                        }
                      ]
                    }
                  }
                ]
              }
            },
            "PARM_DECL:'argc'",
            "PARM_DECL:'argv'"
          ]
        }
      },
      {
        "FUNCTION_DECL:'printHelp'": {
          "children": [
            "COMPOUND_STMT:''",
            "PARM_DECL:''",
            "PARM_DECL:'argv'"
          ]
        }
      },
      "INCLUSION_DIRECTIVE:'pcl/io/oni_grabber.h'",
      "INCLUSION_DIRECTIVE:'pcl/io/pcd_io.h'",
      "INCLUSION_DIRECTIVE:'pcl/point_cloud.h'",
      "INCLUSION_DIRECTIVE:'pcl/point_types.h'",
      "INCLUSION_DIRECTIVE:'vector'",
      {
        "VAR_DECL:'buf'": {
          "children": [
            "INTEGER_LITERAL:''"
          ]
        }
      },
      {
        "VAR_DECL:'i'": {
          "children": [
            "INTEGER_LITERAL:''"
          ]
        }
      }
    ]
  }
}