{
  "TRANSLATION_UNIT:'/pcl/simulation/tools/sim_terminal_demo.cpp'": {
    "children": [
      {
        "FUNCTION_DECL:'printHelp'": {
          "children": [
            "COMPOUND_STMT:''",
            "PARM_DECL:''",
            "PARM_DECL:'argv'"
          ]
        }
      },
      {
        "FUNCTION_DECL:'write_sim_output'": {
          "children": [
            {
              "COMPOUND_STMT:''": {
                "children": [
                  {
                    "DECL_STMT:''": {
                      "children": [
                        "VAR_DECL:'rangeImage'"
                      ]
                    }
                  },
                  {
                    "IF_STMT:''": {
                      "children": [
                        {
                          "COMPOUND_STMT:''": {
                            "children": [
                              {
                                "DECL_STMT:''": {
                                  "children": [
                                    "VAR_DECL:'writer'"
                                  ]
                                }
                              }
                            ]
                          }
                        },
                        "COMPOUND_STMT:''"
                      ]
                    }
                  }
                ]
              }
            },
            {
              "PARM_DECL:'fname_root'": {
                "children": [
                  "NAMESPACE_REF:'std'",
                  "TYPE_REF:'std::string'"
                ]
              }
            }
          ]
        }
      },
      "INCLUSION_DIRECTIVE:'cmath'",
      "INCLUSION_DIRECTIVE:'iostream'",
      "INCLUSION_DIRECTIVE:'pcl/common/time.h'",
      "INCLUSION_DIRECTIVE:'pcl/io/pcd_io.h'",
      "INCLUSION_DIRECTIVE:'pcl/memory.h'",
      "INCLUSION_DIRECTIVE:'simulation_io.hpp'",
      "MACRO_INSTANTIATION:'M_PI'",
      "MACRO_INSTANTIATION:'M_PI'",
      "MACRO_INSTANTIATION:'M_PI'",
      "MACRO_INSTANTIATION:'M_PI'",
      "MACRO_INSTANTIATION:'M_PI'",
      "MACRO_INSTANTIATION:'M_PI'",
      {
        "USING_DIRECTIVE:''": {
          "children": [
            "NAMESPACE_REF:'pcl'"
          ]
        }
      },
      {
        "USING_DIRECTIVE:''": {
          "children": [
            "NAMESPACE_REF:'pcl'",
            "NAMESPACE_REF:'simulation'"
          ]
        }
      },
      "VAR_DECL:'generate_halo'",
      "VAR_DECL:'simexample'"
    ]
  }
}