{
  "TRANSLATION_UNIT:'/pcl/io/include/pcl/io/impl/auto_io.hpp'": {
    "children": [
      "INCLUSION_DIRECTIVE:'boost/filesystem.hpp'",
      "INCLUSION_DIRECTIVE:'pcl/io/ifs_io.h'",
      "INCLUSION_DIRECTIVE:'pcl/io/pcd_io.h'",
      "INCLUSION_DIRECTIVE:'pcl/io/ply_io.h'",
      "MACRO_DEFINITION:'PCL_IO_AUTO_IO_IMPL_H_'",
      {
        "NAMESPACE:'pcl'": {
          "children": [
            {
              "NAMESPACE:'io'": {
                "children": [
                  {
                    "FUNCTION_TEMPLATE:'load'": {
                      "children": [
                        {
                          "COMPOUND_STMT:''": {
                            "children": [
                              {
                                "DECL_STMT:''": {
                                  "children": [
                                    {
                                      "VAR_DECL:'p'": {
                                        "children": [
                                          "NAMESPACE_REF:'boost'",
                                          "NAMESPACE_REF:'filesystem'",
                                          "TYPE_REF:'class boost::filesystem::path'"
                                        ]
                                      }
                                    }
                                  ]
                                }
                              },
                              {
                                "DECL_STMT:''": {
                                  "children": [
                                    {
                                      "VAR_DECL:'extension'": {
                                        "children": [
                                          "NAMESPACE_REF:'std'",
                                          "TYPE_REF:'std::string'",
                                          {
                                            "UNEXPOSED_EXPR:''": {
                                              "children": [
                                                {
                                                  "UNEXPOSED_EXPR:'string'": {
                                                    "children": [
                                                      {
                                                        "CALL_EXPR:'string'": {
                                                          "children": [
                                                            {
                                                              "MEMBER_REF_EXPR:'string'": {
                                                                "children": [
                                                                  {
                                                                    "UNEXPOSED_EXPR:''": {
                                                                      "children": [
                                                                        {
                                                                          "UNEXPOSED_EXPR:''": {
                                                                            "children": [
                                                                              {
                                                                                "CALL_EXPR:'extension'": {
                                                                                  "children": [
                                                                                    {
                                                                                      "MEMBER_REF_EXPR:'extension'": {
                                                                                        "children": [
                                                                                          {
                                                                                            "UNEXPOSED_EXPR:'p'": {
                                                                                              "children": [
                                                                                                "DECL_REF_EXPR:'p'"
                                                                                              ]
                                                                                            }
                                                                                          }
                                                                                        ]
                                                                                      }
                                                                                    }
                                                                                  ]
                                                                                }
                                                                              }
                                                                            ]
                                                                          }
                                                                        }
                                                                      ]
                                                                    }
                                                                  }
                                                                ]
                                                              }
                                                            }
                                                          ]
                                                        }
                                                      }
                                                    ]
                                                  }
                                                }
                                              ]
                                            }
                                          }
                                        ]
                                      }
                                    }
                                  ]
                                }
                              },
                              {
                                "DECL_STMT:''": {
                                  "children": [
                                    {
                                      "VAR_DECL:'result'": {
                                        "children": [
                                          {
                                            "UNARY_OPERATOR:''": {
                                              "children": [
                                                "INTEGER_LITERAL:''"
                                              ]
                                            }
                                          }
                                        ]
                                      }
                                    }
                                  ]
                                }
                              },
                              {
                                "IF_STMT:''": {
                                  "children": [
                                    {
                                      "IF_STMT:''": {
                                        "children": [
                                          {
                                            "IF_STMT:''": {
                                              "children": [
                                                {
                                                  "COMPOUND_STMT:''": {
                                                    "children": [
                                                      {
                                                        "BINARY_OPERATOR:''": {
                                                          "children": [
                                                            "DECL_REF_EXPR:'result'",
                                                            {
                                                              "UNARY_OPERATOR:''": {
                                                                "children": [
                                                                  "INTEGER_LITERAL:''"
                                                                ]
                                                              }
                                                            }
                                                          ]
                                                        }
                                                      }
                                                    ]
                                                  }
                                                },
                                                "NULL_STMT:''"
                                              ]
                                            }
                                          },
                                          "NULL_STMT:''"
                                        ]
                                      }
                                    },
                                    "NULL_STMT:''"
                                  ]
                                }
                              },
                              {
                                "RETURN_STMT:''": {
                                  "children": [
                                    {
                                      "UNEXPOSED_EXPR:''": {
                                        "children": [
                                          {
                                            "PAREN_EXPR:''": {
                                              "children": [
                                                "DECL_REF_EXPR:'result'"
                                              ]
                                            }
                                          }
                                        ]
                                      }
                                    }
                                  ]
                                }
                              }
                            ]
                          }
                        },
                        "PARM_DECL:'cloud'",
                        {
                          "PARM_DECL:'file_name'": {
                            "children": [
                              "NAMESPACE_REF:'std'",
                              "TYPE_REF:'std::string'"
                            ]
                          }
                        },
                        "TEMPLATE_TYPE_PARAMETER:'PointT'"
                      ]
                    }
                  },
                  {
                    "FUNCTION_TEMPLATE:'save'": {
                      "children": [
                        {
                          "COMPOUND_STMT:''": {
                            "children": [
                              {
                                "DECL_STMT:''": {
                                  "children": [
                                    {
                                      "VAR_DECL:'p'": {
                                        "children": [
                                          "NAMESPACE_REF:'boost'",
                                          "NAMESPACE_REF:'filesystem'",
                                          "TYPE_REF:'class boost::filesystem::path'"
                                        ]
                                      }
                                    }
                                  ]
                                }
                              },
                              {
                                "DECL_STMT:''": {
                                  "children": [
                                    {
                                      "VAR_DECL:'extension'": {
                                        "children": [
                                          "NAMESPACE_REF:'std'",
                                          "TYPE_REF:'std::string'",
                                          {
                                            "UNEXPOSED_EXPR:''": {
                                              "children": [
                                                {
                                                  "UNEXPOSED_EXPR:'string'": {
                                                    "children": [
                                                      {
                                                        "CALL_EXPR:'string'": {
                                                          "children": [
                                                            {
                                                              "MEMBER_REF_EXPR:'string'": {
                                                                "children": [
                                                                  {
                                                                    "UNEXPOSED_EXPR:''": {
                                                                      "children": [
                                                                        {
                                                                          "UNEXPOSED_EXPR:''": {
                                                                            "children": [
                                                                              {
                                                                                "CALL_EXPR:'extension'": {
                                                                                  "children": [
                                                                                    {
                                                                                      "MEMBER_REF_EXPR:'extension'": {
                                                                                        "children": [
                                                                                          {
                                                                                            "UNEXPOSED_EXPR:'p'": {
                                                                                              "children": [
                                                                                                "DECL_REF_EXPR:'p'"
                                                                                              ]
                                                                                            }
                                                                                          }
                                                                                        ]
                                                                                      }
                                                                                    }
                                                                                  ]
                                                                                }
                                                                              }
                                                                            ]
                                                                          }
                                                                        }
                                                                      ]
                                                                    }
                                                                  }
                                                                ]
                                                              }
                                                            }
                                                          ]
                                                        }
                                                      }
                                                    ]
                                                  }
                                                }
                                              ]
                                            }
                                          }
                                        ]
                                      }
                                    }
                                  ]
                                }
                              },
                              {
                                "DECL_STMT:''": {
                                  "children": [
                                    {
                                      "VAR_DECL:'result'": {
                                        "children": [
                                          {
                                            "UNARY_OPERATOR:''": {
                                              "children": [
                                                "INTEGER_LITERAL:''"
                                              ]
                                            }
                                          }
                                        ]
                                      }
                                    }
                                  ]
                                }
                              },
                              {
                                "IF_STMT:''": {
                                  "children": [
                                    {
                                      "IF_STMT:''": {
                                        "children": [
                                          {
                                            "IF_STMT:''": {
                                              "children": [
                                                {
                                                  "COMPOUND_STMT:''": {
                                                    "children": [
                                                      {
                                                        "BINARY_OPERATOR:''": {
                                                          "children": [
                                                            "DECL_REF_EXPR:'result'",
                                                            {
                                                              "UNARY_OPERATOR:''": {
                                                                "children": [
                                                                  "INTEGER_LITERAL:''"
                                                                ]
                                                              }
                                                            }
                                                          ]
                                                        }
                                                      }
                                                    ]
                                                  }
                                                },
                                                "NULL_STMT:''"
                                              ]
                                            }
                                          },
                                          "NULL_STMT:''"
                                        ]
                                      }
                                    },
                                    "NULL_STMT:''"
                                  ]
                                }
                              },
                              {
                                "RETURN_STMT:''": {
                                  "children": [
                                    {
                                      "UNEXPOSED_EXPR:''": {
                                        "children": [
                                          {
                                            "PAREN_EXPR:''": {
                                              "children": [
                                                "DECL_REF_EXPR:'result'"
                                              ]
                                            }
                                          }
                                        ]
                                      }
                                    }
                                  ]
                                }
                              }
                            ]
                          }
                        },
                        "PARM_DECL:'cloud'",
                        {
                          "PARM_DECL:'file_name'": {
                            "children": [
                              "NAMESPACE_REF:'std'",
                              "TYPE_REF:'std::string'"
                            ]
                          }
                        },
                        "TEMPLATE_TYPE_PARAMETER:'PointT'"
                      ]
                    }
                  }
                ]
              }
            }
          ]
        }
      }
    ]
  }
}